vireadb/__init__.py
vireadb/common.py
vireadb/compress.py
vireadb/cram.py
vireadb/fasta.py
vireadb/vireadb.py
vireadb-0.0.16.dist-info/LICENSE
vireadb-0.0.16.dist-info/METADATA
vireadb-0.0.16.dist-info/WHEEL
vireadb-0.0.16.dist-info/top_level.txt
vireadb-0.0.16.dist-info/RECORD
