Metadata-Version: 2.1
Name: vireadb
Version: 0.0.16
Summary: ViReaDB: Viral Read Database
Home-page: https://github.com/niemasd/ViReaDB
Author: Niema Moshiri
Author-email: niemamoshiri@gmail.com
License: UNKNOWN
Project-URL: Bug Reports, https://github.com/niemasd/ViReaDB/issues
Project-URL: Source, https://github.com/niemasd/ViReaDB
Keywords: virus sequence database
Platform: UNKNOWN
Classifier: Development Status :: 3 - Alpha
Classifier: Intended Audience :: Developers
Classifier: Topic :: Software Development :: Build Tools
Classifier: License :: OSI Approved :: GNU General Public License v3 or later (GPLv3+)
Classifier: Programming Language :: Python :: 3
Classifier: Programming Language :: Python :: 3.4
Classifier: Programming Language :: Python :: 3.5
Classifier: Programming Language :: Python :: 3.6
Requires-Dist: numpy
Requires-Dist: pysam
Provides-Extra: dev
Requires-Dist: check-manifest ; extra == 'dev'
